xuebadb
