Metadata-Version: 2.1
Name: xuebadb
Version: 1.3
Summary: xuebadb is a python package that allows users to conveniently connect to and query from various database systems using a unified API. Currently, it supports connecting to MySQL and SQL Server database systems. The queries return Pandas dataframes which can then be cleaned up and analysed using one of the modules in the package.
Home-page: https://github.com/vaghulb1992/xuebadb
Author: Vaghul Aditya Balaji
Author-email: vaghulb1992@gmail.com
License: MIT
Platform: UNKNOWN
Requires-Python: >=3
